pr_pilot/__init__.py
pr_pilot/api/__init__.py
pr_pilot/api/pr_retrieval_api.py
pr_pilot/api/task_creation_api.py
pr_pilot/api/task_retrieval_api.py
pr_pilot/api_client.py
pr_pilot/api_response.py
pr_pilot/configuration.py
pr_pilot/docs/BadRequest.md
pr_pilot/docs/NotFound.md
pr_pilot/docs/PRNumberResponse.md
pr_pilot/docs/PRRetrievalApi.md
pr_pilot/docs/Prompt.md
pr_pilot/docs/RepoBranchInput.md
pr_pilot/docs/Task.md
pr_pilot/docs/TaskCreationApi.md
pr_pilot/docs/TaskRetrievalApi.md
pr_pilot/exceptions.py
pr_pilot/models/__init__.py
pr_pilot/models/bad_request.py
pr_pilot/models/not_found.py
pr_pilot/models/pr_number_response.py
pr_pilot/models/prompt.py
pr_pilot/models/repo_branch_input.py
pr_pilot/models/task.py
pr_pilot/rest.py
pr_pilot/test/__init__.py
pr_pilot/test/test_bad_request.py
pr_pilot/test/test_not_found.py
pr_pilot/test/test_pr_number_response.py
pr_pilot/test/test_pr_retrieval_api.py
pr_pilot/test/test_prompt.py
pr_pilot/test/test_repo_branch_input.py
pr_pilot/test/test_task.py
pr_pilot/test/test_task_creation_api.py
pr_pilot/test/test_task_retrieval_api.py
pr_pilot/util.py
pr_pilot-1.7.0.dist-info/LICENSE
pr_pilot-1.7.0.dist-info/METADATA
pr_pilot-1.7.0.dist-info/WHEEL
pr_pilot-1.7.0.dist-info/RECORD
