Metadata-Version: 2.1
Name: pr-pilot
Version: 1.7.0
Summary: Python SDK for PR Pilot, a text-to-task automation platform for Github.
Home-page: https://github.com/PR-Pilot-AI/pr-pilot-python
License: GPL-3.0
Author: Marco Lamina
Author-email: marco@pr-pilot.ai
Requires-Python: >=3.10
Classifier: License :: OSI Approved :: GNU General Public License v3 (GPLv3)
Classifier: Programming Language :: Python :: 3
Classifier: Programming Language :: Python :: 3.10
Classifier: Programming Language :: Python :: 3.11
Classifier: Programming Language :: Python :: 3.12
Requires-Dist: pydantic (<2.7)
Requires-Dist: python-dateutil (==2.9.0)
Requires-Dist: urllib3 (==2.2.1)
Requires-Dist: wheel (==0.42.0)
Project-URL: Repository, https://github.com/PR-Pilot-AI/pr-pilot-python
